pgqrs/__init__.py
pgqrs/__init__.pyi
pgqrs/_pgqrs.pypy39-pp73-aarch64-linux-gnu.so
pgqrs/decorators.py
pgqrs-0.13.0.dist-info/METADATA
pgqrs-0.13.0.dist-info/WHEEL
pgqrs-0.13.0.dist-info/RECORD
