Metadata-Version: 2.4
Name: pgqrs
Version: 0.13.0
Classifier: Programming Language :: Rust
Classifier: Programming Language :: Python :: Implementation :: CPython
Classifier: Programming Language :: Python :: Implementation :: PyPy
Classifier: Development Status :: 4 - Beta
Classifier: Intended Audience :: Developers
Classifier: License :: OSI Approved :: MIT License
Classifier: License :: OSI Approved :: Apache Software License
Requires-Dist: psycopg[binary]>=3.0
Requires-Dist: pytest>=7.0 ; extra == 'test'
Requires-Dist: pytest-asyncio>=0.21 ; extra == 'test'
Requires-Dist: testcontainers[postgres]>=3.7 ; extra == 'test'
Requires-Dist: urllib3<2.0 ; extra == 'test'
Provides-Extra: test
Summary: PostgreSQL-backed job queue with Rust and Python bindings
Keywords: postgresql,queue,task-queue,background-jobs,job-queue
Author: Rajat Venkatesh
License-Expression: MIT OR Apache-2.0
Requires-Python: >=3.11
Project-URL: Documentation, https://github.com/vrajat/pgqrs
Project-URL: Homepage, https://github.com/vrajat/pgqrs
Project-URL: Issue Tracker, https://github.com/vrajat/pgqrs/issues
Project-URL: Repository, https://github.com/vrajat/pgqrs
